xyz2graph/__init__.py
xyz2graph/cli.py
xyz2graph/constants.py
xyz2graph/graph.py
xyz2graph/helpers.py
xyz2graph/logging.py
xyz2graph/molecule.py
xyz2graph/visualization.py
xyz2graph-3.5.0.dist-info/METADATA
xyz2graph-3.5.0.dist-info/WHEEL
xyz2graph-3.5.0.dist-info/entry_points.txt
xyz2graph-3.5.0.dist-info/licenses/LICENSE
xyz2graph-3.5.0.dist-info/RECORD
