Metadata-Version: 2.4
Name: xyz2graph
Version: 3.5.0
Summary: Package for reading of .xyz files and constructing of molecular graphs from atomic coordinates.
Project-URL: Homepage, https://github.com/zotko/xyz2graph
Project-URL: Repository, https://github.com/zotko/xyz2graph
Project-URL: Documentation, https://zotko.github.io/xyz2graph
Project-URL: Bug Tracker, https://github.com/zotko/xyz2graph/issues
Author-email: Mykola Zotko <dev.zotko@outlook.de>
License: ISC License
License-File: LICENSE
Keywords: chemistry,molecular-graphs,visualization,xyz-files
Classifier: Development Status :: 5 - Production/Stable
Classifier: Intended Audience :: Science/Research
Classifier: License :: OSI Approved :: ISC License (ISCL)
Classifier: Operating System :: OS Independent
Classifier: Programming Language :: Python :: 3
Classifier: Programming Language :: Python :: 3.8
Classifier: Programming Language :: Python :: 3.9
Classifier: Programming Language :: Python :: 3.10
Classifier: Programming Language :: Python :: 3.11
Classifier: Programming Language :: Python :: 3.12
Classifier: Topic :: Scientific/Engineering :: Chemistry
Classifier: Topic :: Scientific/Engineering :: Visualization
Requires-Python: >=3.8
Requires-Dist: networkx>=2.6.0
Requires-Dist: numpy>=1.21.0
Requires-Dist: plotly>=5.0.0
Provides-Extra: dev
Requires-Dist: build<2.0.0,>=1.0.0; extra == 'dev'
Requires-Dist: mypy<2.0.0,>=1.0.0; extra == 'dev'
Requires-Dist: pre-commit>=3.5.0; extra == 'dev'
Requires-Dist: pytest-cov<5.0.0,>=4.0.0; extra == 'dev'
Requires-Dist: pytest<8.0.0,>=7.0.0; extra == 'dev'
Requires-Dist: ruff<1.0.0,>=0.1.0; extra == 'dev'
Requires-Dist: twine<5.0.0,>=4.0.0; extra == 'dev'
Provides-Extra: docs
Requires-Dist: mkdocs-include-markdown-plugin; extra == 'docs'
Requires-Dist: mkdocs-material>=9.5.0; extra == 'docs'
Requires-Dist: mkdocs>=1.6.0; extra == 'docs'
Requires-Dist: mkdocstrings[python]>=0.18; extra == 'docs'
